{"Go (1.6)": 7, "Java7 (OpenJDK 1.7.0)": 5, "Rust (1.15.1)": 2, "Common Lisp (SBCL 1.1.14)": 2, "Python3 (3.4.3)": 55, "Nim (0.13.0)": 1, "C++14 (Clang 3.8.0)": 7, "JavaScript (node.js v5.12)": 1, "PyPy3 (2.4.0)": 1, "C (Clang 3.8.0)": 2, "PyPy2 (5.6.0)": 1, "C++14 (GCC 5.4.1)": 248, "Haskell (GHC 7.10.3)": 9, "C (GCC 5.4.1)": 29, "Perl (v5.18.2)": 2, "Java8 (OpenJDK 1.8.0)": 26, "Ruby (2.3.3)": 23, "Kotlin (1.0.0)": 1, "PHP (5.6.30)": 3, "TypeScript (2.1.6)": 1, "Python2 (2.7.6)": 17, "C# (Mono 4.6.2.0)": 22}