{"Java7 (OpenJDK 1.7.0)": 21, "Perl (5.26.1)": 2, "Swift (5.2.1)": 15, "Dart (2.7.2)": 4, "bc (1.07.1)": 1, "Clojure (1.8.0)": 3, "PyPy3 (2.4.0)": 507, "PHP (5.6.30)": 23, "PHP (7.4.4)": 15, "Ruby (2.7.1)": 68, "Erlang (22.3)": 1, "Kotlin (1.0.0)": 58, "TypeScript (3.8)": 8, "COBOL - Free (OpenCOBOL 1.1.0)": 1, "Java (OpenJDK 1.8.0)": 13, "Haskell (GHC 7.10.3)": 92, "MoonScript (0.5.0)": 1, "TypeScript (2.1.6)": 11, "Visual Basic (Mono 4.0.1)": 5, "Crystal (0.20.5)": 6, "C++14 (Clang 3.8.0)": 145, "Haskell (GHC 8.8.3)": 7, "OCaml (4.02.3)": 15, "C++11 (GCC 4.8.1)": 2, "Bash (5.0.11)": 1, "Fortran (gfortran v4.8.4)": 16, "C (Clang 3.8.0)": 13, "C++ (GCC 5.4.1)": 163, "JavaScript (node.js v5.12)": 71, "Pascal (FPC 3.0.4)": 1, "Objective-C (Clang3.8.0)": 3, "Elixir (1.10.2)": 2, "Lua (5.3.2)": 5, "COBOL - Fixed (OpenCOBOL 1.1.0)": 1, "Visual Basic (.NET Core 3.1.101)": 2, "D (DMD64 v2.070.1)": 31, "C++14 (GCC 5.4.1)": 5747, "C (GCC 5.4.1)": 265, "Common Lisp (SBCL 1.1.14)": 12, "D (LDC 0.17.0)": 3, "Awk (mawk 1.3.3)": 4, "Scheme (Gauche 0.9.3.3)": 10, "PyPy2 (7.3.0)": 1, "C++ (Clang 10.0.0)": 70, "Clojure (1.10.1.536)": 1, "Java (OpenJDK 11.0.6)": 109, "C# (Mono-mcs 6.8.0.105)": 5, "Perl (v5.18.2)": 16, "Julia (1.4.0)": 8, "Brainfuck (bf 20041219)": 2, "Standard ML (MLton 20100608)": 1, "Common Lisp (SBCL 2.0.3)": 2, "C# (Mono-csc 3.5.0)": 2, "LuaJIT (2.0.4)": 3, "Python2 (2.7.6)": 39, "PyPy2 (5.6.0)": 1, "Scala (2.11.7)": 25, "Crystal (0.33.0)": 4, "Go (1.6)": 195, "Nim (1.0.6)": 5, "Rust (1.15.1)": 151, "C++ (Clang 3.8.0)": 10, "F# (.NET Core 3.1.201)": 6, "D (DMD 2.091.0)": 2, "Fortran (GNU Fortran 9.2.1)": 6, "OCaml (4.10.0)": 5, "C++ (GCC 9.2.1)": 1438, "Rust (1.42.0)": 76, "Java8 (OpenJDK 1.8.0)": 576, "Objective-C (GCC 5.3.0)": 1, "PyPy3 (7.3.0)": 334, "C (Clang 10.0.0)": 8, "JavaScript (Node.js 12.16.1)": 35, "Lua (Lua 5.3.5)": 1, "C (GCC 9.2.1)": 59, "F# (Mono 10.2.3)": 2, "Ruby (2.3.3)": 372, "Nim (0.13.0)": 28, "Octave (4.0.2)": 9, "Awk (GNU Awk 4.1.4)": 12, "Swift (swift-2.2-RELEASE)": 5, "F# (Mono 4.0)": 10, "Scala (2.13.1)": 8, "D (GDC 4.9.4)": 1, "Bash (GNU bash v4.3.11)": 7, "Sed (GNU sed 4.2.2)": 5, "Julia (0.5.0)": 6, "C# (.NET Core 3.1.201)": 56, "Go (1.14.1)": 50, "C# (Mono 4.6.2.0)": 257, "Python (3.8.2)": 1128, "Fortran(GNU Fortran 9.2.1)": 3, "Python3 (3.4.3)": 3439, "Pascal (FPC 2.6.2)": 15, "Kotlin (1.3.71)": 9, "PHP7 (7.0.15)": 30}