{"PyPy2 (7.3.0)": 4, "Fortran (GNU Fortran 9.2.1)": 6, "Python (3.8.2)": 1178, "Crystal (0.33.0)": 3, "Haskell (GHC 8.8.3)": 9, "Java (OpenJDK 1.8.0)": 27, "PHP (7.4.4)": 9, "Scala (2.13.1)": 8, "C (GCC 9.2.1)": 67, "C# (.NET Core 3.1.201)": 74, "JavaScript (Node.js 12.16.1)": 15, "F# (.NET Core 3.1.201)": 3, "PyPy3 (7.3.0)": 553, "Ruby (2.7.1)": 90, "Pascal (FPC 3.0.4)": 2, "C++ (GCC 9.2.1)": 3687, "Octave (5.2.0)": 1, "Lua (LuaJIT 2.1.0)": 1, "Elixir (1.10.2)": 1, "Nim (1.0.6)": 3, "Java (OpenJDK 11.0.6)": 185, "OCaml (4.10.0)": 2, "C# (Mono-mcs 6.8.0.105)": 6, "C# (Mono-csc 3.5.0)": 1, "Dart (2.7.2)": 2, "C++ (Clang 10.0.0)": 130, "Rust (1.42.0)": 88, "Perl (5.26.1)": 4, "Swift (5.2.1)": 15, "Visual Basic (.NET Core 3.1.101)": 2, "Raku (Rakudo 2020.02.1)": 3, "Go (1.14.1)": 43, "D (DMD 2.091.0)": 9, "C (Clang 10.0.0)": 8, "Common Lisp (SBCL 2.0.3)": 5, "Cython (0.29.16)": 1, "TypeScript (3.8)": 2, "Julia (1.4.0)": 8, "Kotlin (1.3.71)": 23}