{"PyPy2 (7.3.0)": 3, "Fortran (GNU Fortran 9.2.1)": 2, "Python (3.8.2)": 246, "Crystal (0.33.0)": 4, "PHP (7.4.4)": 5, "Java (OpenJDK 1.8.0)": 12, "Haskell (GHC 8.8.3)": 5, "Scala (2.13.1)": 2, "C (GCC 9.2.1)": 9, "C# (.NET Core 3.1.201)": 49, "JavaScript (Node.js 12.16.1)": 4, "PyPy3 (7.3.0)": 483, "Ruby (2.7.1)": 38, "C++ (GCC 9.2.1)": 2855, "Lua (LuaJIT 2.1.0)": 1, "Nim (1.0.6)": 6, "Java (OpenJDK 11.0.6)": 100, "OCaml (4.10.0)": 3, "C# (Mono-mcs 6.8.0.105)": 2, "C++ (Clang 10.0.0)": 96, "Rust (1.42.0)": 96, "Swift (5.2.1)": 13, "Go (1.14.1)": 22, "D (DMD 2.091.0)": 6, "C (Clang 10.0.0)": 1, "Common Lisp (SBCL 2.0.3)": 6, "Cython (0.29.16)": 10, "D (LDC 1.20.1)": 1, "TypeScript (3.8)": 2, "Kotlin (1.3.71)": 34}