{"Java (OpenJDK 11.0.6)": 123, "Kotlin (1.3.71)": 19, "PyPy2 (7.3.0)": 6, "Rust (1.42.0)": 51, "Nim (1.0.6)": 8, "C++ (Clang 10.0.0)": 83, "C# (.NET Core 3.1.201)": 51, "Fortran(GNU Fortran 9.2.1)": 5, "Python (3.8.2)": 686, "Julia (1.4.0)": 5, "PHP (7.4.4)": 7, "PyPy3 (7.3.0)": 385, "C (Clang 10.0.0)": 3, "OCaml (4.10.0)": 3, "C# (Mono-mcs 6.8.0.105)": 5, "Awk (GNU Awk 4.1.4)": 1, "JavaScript (Node.js 12.16.1)": 6, "D (DMD 2.091.0)": 6, "Crystal (0.33.0)": 2, "Lua (Lua 5.3.5)": 1, "C (GCC 9.2.1)": 30, "Go (1.14.1)": 23, "C++ (GCC 9.2.1)": 2969, "Common Lisp (SBCL 2.0.3)": 1, "Cython (0.29.16)": 1, "Haskell (GHC 8.8.3)": 6, "Swift (5.2.1)": 1, "Scala (2.13.1)": 4, "C# (Mono-csc 3.5.0)": 4, "Java (OpenJDK 1.8.0)": 29, "Ruby (2.7.1)": 43}