{"PyPy2 (7.3.0)": 14, "Awk (GNU Awk 4.1.4)": 4, "Python (3.8.2)": 2185, "Crystal (0.33.0)": 4, "PHP (7.4.4)": 17, "Java (OpenJDK 1.8.0)": 62, "Haskell (GHC 8.8.3)": 26, "Scala (2.13.1)": 8, "C (GCC 9.2.1)": 104, "C# (.NET Core 3.1.201)": 143, "COBOL - Free (OpenCOBOL 1.1.0)": 1, "Fortran(GNU Fortran 9.2.1)": 7, "JavaScript (Node.js 12.16.1)": 21, "F# (.NET Core 3.1.201)": 3, "PyPy3 (7.3.0)": 917, "Ruby (2.7.1)": 147, "C++ (GCC 9.2.1)": 7236, "Lua (LuaJIT 2.1.0)": 2, "Nim (1.0.6)": 24, "Java (OpenJDK 11.0.6)": 353, "OCaml (4.10.0)": 12, "C# (Mono-mcs 6.8.0.105)": 10, "C# (Mono-csc 3.5.0)": 7, "C++ (Clang 10.0.0)": 270, "Rust (1.42.0)": 172, "Perl (5.26.1)": 5, "Swift (5.2.1)": 10, "Go (1.14.1)": 84, "D (DMD 2.091.0)": 16, "C (Clang 10.0.0)": 9, "Lua (Lua 5.3.5)": 5, "Haxe (4.0.3); Java": 1, "Common Lisp (SBCL 2.0.3)": 5, "bc (1.07.1)": 2, "Cython (0.29.16)": 5, "TypeScript (3.8)": 5, "Julia (1.4.0)": 10, "Kotlin (1.3.71)": 51}