{"OCaml (4.02.1)": 2, "C++ (GCC 4.9.2)": 114, "C++14 (Clang++ 3.4)": 7, "D (DMD 2.066.1)": 6, "PHP (PHP 5.5.21)": 2, "C (Clang 3.4)": 1, "Java8 (OpenJDK 1.8.0)": 12, "Perl (5.14.2)": 5, "C# (Mono 3.2.1.0)": 14, "Haskell (Haskell Platform 2014.2.0.0)": 7, "Ruby (2.1.5p273)": 20, "Java (OpenJDK 1.7.0)": 35, "C++11 (GCC 4.9.2)": 70, "Python3 (3.4.2)": 15, "Python (2.7.3)": 25, "C++11 (Clang++ 3.4)": 2, "C++11 (GCC 4.8.1)": 2, "Go (1.4.1)": 2, "Bash (4.2.25)": 1, "Common Lisp (SBCL 1.0.55.0)": 1, "Ruby (1.9.3p550)": 4, "C (GCC 4.9.2)": 15}