{"Brainfuck (bf 20041219)": 1, "dc (1.4.1)": 6, "C++14 (Clang 3.8.0)": 24, "C (GCC 9.2.1)": 6, "Cython (0.29.16)": 1, "Haskell (GHC 8.8.3)": 1, "Ruby (2.3.3)": 35, "Nim (0.13.0)": 5, "C++11 (GCC 4.8.1)": 1, "OCaml (4.02.3)": 5, "Octave (4.0.2)": 1, "bc (1.07.1)": 2, "Awk (GNU Awk 4.1.4)": 2, "Bash (5.0.11)": 1, "Fortran (gfortran v4.8.4)": 3, "F# (Mono 4.0)": 2, "Python2 (2.7.6)": 5, "C (Clang 3.8.0)": 4, "PyPy3 (2.4.0)": 46, "JavaScript (node.js v5.12)": 5, "C++ (GCC 5.4.1)": 3, "Java (OpenJDK 11.0.6)": 4, "PyPy2 (5.6.0)": 1, "Scala (2.11.7)": 5, "Lua (5.3.2)": 1, "D (DMD64 v2.070.1)": 10, "Crystal (0.33.0)": 1, "Julia (0.5.0)": 4, "Go (1.6)": 12, "C# (.NET Core 3.1.201)": 2, "C++14 (GCC 5.4.1)": 838, "C# (Mono 4.6.2.0)": 31, "C (GCC 5.4.1)": 29, "Nim (1.0.6)": 2, "Python (3.8.2)": 51, "Common Lisp (SBCL 1.1.14)": 2, "Rust (1.15.1)": 12, "C++ (Clang 3.8.0)": 3, "D (LDC 0.17.0)": 2, "Ruby (2.7.1)": 7, "Kotlin (1.0.0)": 1, "D (DMD 2.091.0)": 1, "Python3 (3.4.3)": 337, "Awk (mawk 1.3.3)": 2, "Pascal (FPC 2.6.2)": 1, "OCaml (4.10.0)": 1, "Haskell (GHC 7.10.3)": 9, "C++ (GCC 9.2.1)": 127, "Rust (1.42.0)": 3, "TypeScript (2.1.6)": 1, "Java8 (OpenJDK 1.8.0)": 62, "Objective-C (GCC 5.3.0)": 1, "Scheme (Gauche 0.9.3.3)": 2, "PHP7 (7.0.15)": 2, "PyPy3 (7.3.0)": 28, "C++ (Clang 10.0.0)": 2, "Crystal (0.20.5)": 1, "Perl (v5.18.2)": 4}