{"C++ (GCC 5.4.1)": 4, "JavaScript (Node.js v0.10.36)": 2, "C++ (GCC 4.9.2)": 149, "Go (1.6)": 3, "Rust (1.15.1)": 12, "Common Lisp (SBCL 1.1.14)": 5, "C++11 (GCC 4.8.1)": 6, "Python (2.7.3)": 11, "Python3 (3.4.3)": 42, "Nim (0.13.0)": 1, "C (GCC 4.9.2)": 19, "C++14 (Clang 3.8.0)": 6, "Nim (1.0.6)": 3, "C++ (Clang 10.0.0)": 3, "PyPy3 (2.4.0)": 45, "C# (.NET Core 3.1.201)": 5, "Haskell (Haskell Platform 2014.2.0.0)": 7, "Fortran(GNU Fortran 9.2.1)": 1, "Python (3.8.2)": 25, "D (DMD 2.066.1)": 2, "PyPy3 (7.3.0)": 39, "OCaml (4.02.3)": 1, "Python3 (3.4.2)": 11, "Java (OpenJDK 1.7.0)": 24, "Ruby (2.1.5p273)": 23, "C++14 (Clang++ 3.4)": 11, "OCaml (4.10.0)": 1, "LuaJIT (2.0.4)": 1, "C++11 (GCC 4.9.2)": 209, "C++14 (GCC 5.4.1)": 299, "Perl (5.14.2)": 1, "D (DMD 2.091.0)": 1, "Ruby (1.9.3p550)": 1, "D (LDC 0.17.0)": 1, "C (GCC 9.2.1)": 2, "C (GCC 5.4.1)": 7, "Go (1.14.1)": 1, "C++ (GCC 9.2.1)": 132, "Java8 (OpenJDK 1.8.0)": 27, "C++11 (Clang++ 3.4)": 4, "Haskell (GHC 8.8.3)": 1, "Bash (4.2.25)": 4, "Ruby (2.3.3)": 4, "D (DMD64 v2.070.1)": 4, "Java (OpenJDK 11.0.6)": 2, "Ruby (2.7.1)": 1, "C# (Mono 3.2.1.0)": 30, "C# (Mono 4.6.2.0)": 10}