{"Pascal (FPC 2.6.2)": 1, "C++ (GCC 5.4.1)": 19, "Go (1.6)": 22, "Scala (2.11.7)": 3, "Java7 (OpenJDK 1.7.0)": 1, "Common Lisp (SBCL 1.1.14)": 2, "C++ (Clang 3.8.0)": 2, "Rust (1.15.1)": 32, "Lua (5.3.2)": 2, "C++11 (GCC 4.8.1)": 1, "Python3 (3.4.3)": 747, "Nim (0.13.0)": 6, "C++14 (Clang 3.8.0)": 34, "PyPy3 (2.4.0)": 142, "JavaScript (node.js v5.12)": 2, "Crystal (0.20.5)": 2, "PHP7 (7.0.15)": 3, "C (Clang 3.8.0)": 5, "OCaml (4.02.3)": 1, "PyPy2 (5.6.0)": 6, "Fortran (gfortran v4.8.4)": 4, "C++14 (GCC 5.4.1)": 1985, "Haskell (GHC 7.10.3)": 11, "Julia (0.5.0)": 2, "D (LDC 0.17.0)": 1, "C (GCC 5.4.1)": 42, "Perl (v5.18.2)": 1, "Java8 (OpenJDK 1.8.0)": 110, "Ruby (2.3.3)": 51, "Kotlin (1.0.0)": 8, "D (DMD64 v2.070.1)": 8, "Python2 (2.7.6)": 1, "C# (Mono 4.6.2.0)": 46}