{"Java7 (OpenJDK 1.7.0)": 2, "Racket (7.6)": 1, "Brainfuck (bf 20041219)": 14, "Standard ML (MLton 20100608)": 1, "dc (1.4.1)": 2, "C++14 (Clang 3.8.0)": 8, "C (GCC 9.2.1)": 13, "Ruby (2.3.3)": 35, "Unlambda (0.1.3)": 2, "Nim (0.13.0)": 6, "OCaml (4.02.3)": 6, "C++11 (GCC 4.8.1)": 1, "Octave (4.0.2)": 2, "Forth (gforth 0.7.3)": 1, "LuaJIT (2.0.4)": 1, "bc (1.07.1)": 1, "Swift (swift-2.2-RELEASE)": 3, "Ada2012 (GNAT 9.2.1)": 1, "Clojure (1.8.0)": 1, "Fortran (gfortran v4.8.4)": 4, "F# (Mono 4.0)": 1, "D (GDC 4.9.4)": 1, "Haxe (4.0.3); Java": 1, "Python2 (2.7.6)": 17, "C (Clang 3.8.0)": 4, "PyPy3 (2.4.0)": 26, "C++ (GCC 5.4.1)": 287, "JavaScript (node.js v5.12)": 7, "Objective-C (Clang3.8.0)": 2, "Haxe (4.0.3); js": 1, "PyPy2 (5.6.0)": 1, "Bash (GNU bash v4.3.11)": 7, "Scala (2.11.7)": 4, "Lua (5.3.2)": 2, "COBOL - Fixed (OpenCOBOL 1.1.0)": 1, "D (DMD64 v2.070.1)": 8, "Crystal (0.33.0)": 1, "Julia (0.5.0)": 7, "Go (1.6)": 8, "PHP (5.6.30)": 8, "C# (.NET Core 3.1.201)": 1, "C++14 (GCC 5.4.1)": 740, "Go (1.14.1)": 2, "C# (Mono 4.6.2.0)": 33, "C (GCC 5.4.1)": 51, "Python (3.8.2)": 30, "Common Lisp (SBCL 1.1.14)": 2, "Rust (1.15.1)": 8, "Ruby (2.7.1)": 2, "D (LDC 0.17.0)": 1, "Perl6 (rakudo-star 2016.01)": 4, "Text (cat)": 139, "Bash (5.0.11)": 1, "Kotlin (1.0.0)": 3, "Text (cat 8.28)": 9, "Crystal (0.20.5)": 2, "COBOL - Free (OpenCOBOL 1.1.0)": 1, "Python3 (3.4.3)": 231, "Awk (mawk 1.3.3)": 2, "Pascal (FPC 2.6.2)": 26, "Haskell (GHC 7.10.3)": 15, "MoonScript (0.5.0)": 1, "C++ (GCC 9.2.1)": 117, "Rust (1.42.0)": 4, "TypeScript (2.1.6)": 2, "Java8 (OpenJDK 1.8.0)": 56, "Objective-C (GCC 5.3.0)": 3, "Scheme (Gauche 0.9.3.3)": 2, "PHP7 (7.0.15)": 4, "PyPy3 (7.3.0)": 8, "Visual Basic (Mono 4.0.1)": 2, "Java (OpenJDK 11.0.6)": 16, "Perl (v5.18.2)": 2, "Julia (1.4.0)": 1}